apps/__init__.py
apps/bond_demo/__init__.py
apps/bond_demo/pullout_hardening.py
apps/bond_demo/pullout_softening.py
apps/sandbox/__init__.py
apps/sandbox/pullout_sketch.py
apps/sandbox/pullout_test_data_generator.py
apps/sandbox/fahad/R-Curve.png
apps/sandbox/fahad/SLIDE_damage_plasticity_tension_cap2.py
apps/sandbox/fahad/Threepointbendingbeam.png
apps/sandbox/fahad/__init__.py
apps/sandbox/fahad/bond_slip_cum_damage_trash.py
apps/sandbox/fahad/crack.png
apps/sandbox/fahad/cracktipzoom.png
apps/sandbox/fahad/f_name.png
apps/sandbox/fahad/farfieldstress.png
apps/sandbox/fahad/fixedcrackapproach.png
apps/sandbox/fahad/gfdistribution.png
apps/sandbox/fahad/microplane.png
apps/sandbox/fahad/moment_curvature.py
apps/sandbox/fahad/new2dmatmodel.py
apps/sandbox/fahad/norm_force_axisym.py
apps/sandbox/fahad/plotting_example.py
apps/sandbox/fahad/plotting_sigma_N.py
apps/sandbox/fahad/pulloutaxisymdemomodel.py
apps/sandbox/fahad/shear crack representation.png
apps/sandbox/fahad/sigNfortau10000lp5000.txt
apps/sandbox/fahad/sigma_N_plot_lateralpressure.py
apps/sandbox/fahad/smearedcrackapproach.png
apps/sandbox/fahad/stressopeningrelation.png
apps/sandbox/fahad/verify02_bond_slip_2d_cum_damage.py
apps/sandbox/fahad/verify03_bond_slip.py
apps/sandbox/fahad/verify041_normalized_max_pullout.py
apps/sandbox/fahad/vmats1d5_dp_new.py
apps/sandbox/fahad/vmats1d5_newmodel.py
apps/sandbox/homam/__init__.py
apps/sandbox/homam/test_imports.py
apps/sandbox/mario/__init__.py
apps/sandbox/mario/data_filtering.py
apps/sandbox/mario/hcff_homam.py
apps/sandbox/mario/hcff_rostia_mario_methods.py
apps/sandbox/mario/something_traits.py
apps/sandbox/neural_netrworks/__init__.py
apps/sandbox/neural_netrworks/outputs.txt
apps/sandbox/neural_netrworks/pullout_sketch.py
apps/sandbox/neural_netrworks/pullout_test_data_generator.py
apps/sandbox/neural_netrworks/pullout_test_data_generator2.py
apps/sandbox/rch/__init__.py
apps/sandbox/rch/lattice_example/__init__.py
bmcs-0.0.2a46.dist-info/METADATA
bmcs-0.0.2a46.dist-info/WHEEL
bmcs-0.0.2a46.dist-info/entry_points.txt
bmcs-0.0.2a46.dist-info/top_level.txt
bmcs-0.0.2a46.dist-info/RECORD
